pawel_package/__init__.py
pawel_package/package_file.py
example_zagorskipawel-0.0.1.dist-info/LICENSE
example_zagorskipawel-0.0.1.dist-info/METADATA
example_zagorskipawel-0.0.1.dist-info/WHEEL
example_zagorskipawel-0.0.1.dist-info/top_level.txt
example_zagorskipawel-0.0.1.dist-info/RECORD
