Metadata-Version: 2.1
Name: example-zagorskipawel
Version: 0.0.1
Summary: A small example package created for TTTech recruitment
Home-page: UNKNOWN
Author: Pawel Zagorski
Author-email: pawel.zagorski.to@gmail.com
License: UNKNOWN
Platform: UNKNOWN
Classifier: Programming Language :: Python :: 3
Classifier: Operating System :: OS Independent
Requires-Python: >=3.6
License-File: LICENSE
